{"action":{"action":"merge_stack","source":{"board_cards":[{"card":{"value":1,"suit":2,"origin_deck":0},"state":0}],"loc":{"top":180,"left":425}},"target":{"board_cards":[{"card":{"value":1,"suit":0,"origin_deck":1},"state":0}],"loc":{"top":64,"left":320}},"side":"right"},"gesture_metadata":{"path":[{"t":135585,"x":425,"y":180},{"t":135647,"x":424,"y":180},{"t":135679,"x":423,"y":179},{"t":135679,"x":416,"y":168},{"t":135694,"x":407,"y":154},{"t":135709,"x":397,"y":136},{"t":135725,"x":387,"y":118},{"t":135740,"x":380,"y":108},{"t":135772,"x":373,"y":96},{"t":135788,"x":370,"y":91},{"t":135804,"x":367,"y":87},{"t":135819,"x":367,"y":85},{"t":135819,"x":366,"y":84},{"t":135851,"x":366,"y":83},{"t":136007,"x":365,"y":81},{"t":136007,"x":365,"y":80},{"t":136147,"x":365,"y":79},{"t":136147,"x":365,"y":77},{"t":136179,"x":365,"y":75},{"t":136194,"x":364,"y":74},{"t":136210,"x":364,"y":72},{"t":136226,"x":363,"y":71},{"t":136241,"x":363,"y":70},{"t":136272,"x":361,"y":68},{"t":136304,"x":360,"y":68},{"t":136304,"x":360,"y":67},{"t":136335,"x":358,"y":67},{"t":136366,"x":357,"y":66},{"t":136397,"x":356,"y":66},{"t":136444,"x":355,"y":66},{"t":136460,"x":354,"y":66},{"t":136460,"x":351,"y":66},{"t":136726,"x":351,"y":66}],"path_frame":"board","pointer_type":"mouse"},"puzzle_name":"stunning_puzzle"}